{
  "cached_at": "2025-08-30T02:19:20.027982",
  "data": {
    "parts": [
      {
        "id": 12,
        "part": "industry",
        "name": "Branche",
        "info": "Her kan du indsn칝vre s칮gningen til kun at omfatte bestemte brancher, s친dan som de fremg친r af registreringen i CVR. Dvs. at du kun f친r hit, hvis en virksomhed inden for den p친g칝ldende branche indg친r i oplysningerne fra Tinglysningen. Der er i alt 742 brancher. Hvis du ikke v칝lger en branche, bruger vi ikke dette til at afgr칝nse uds칮gningen, dvs. du har i praksis valgt alle brancher.",
        "slug": "branche",
        "canSelectMultiple": true,
        "order": 1
      },
      {
        "id": 13,
        "part": "company",
        "name": "Virksomhed",
        "info": "",
        "slug": "virksomhed",
        "canSelectMultiple": true,
        "order": 2
      },
      {
        "id": 14,
        "part": "municipality",
        "name": "Kommune",
        "info": "Her kan du v칝lge blandt 98 kommuner, som du vil overv친ge. Christians칮 optr칝der nogle steder som en selvst칝ndig kommune - idet data herfra ikke er tilknyttet en eksisterende kommune. Endelig vil der v칝re mulighed for at v칝lge uoplyst, hvor data ikke kan knyttes til en kommune. Klikker du ikke kommuner ud, har du i praksis valgt alt, ogs친 uoplyst og Christians칮.",
        "slug": "kommune",
        "canSelectMultiple": true,
        "order": 3
      },
      {
        "id": 17,
        "part": "person",
        "name": "Person",
        "info": "",
        "slug": "person",
        "canSelectMultiple": true,
        "order": 4
      },
      {
        "id": 15,
        "part": "search_string",
        "name": "S칮geord",
        "info": "",
        "slug": "soegeord",
        "canSelectMultiple": true,
        "order": 5
      },
      {
        "id": 16,
        "part": "hit_logic",
        "name": "Hitlogik",
        "info": "",
        "slug": "hitlogik",
        "canSelectMultiple": false,
        "order": 6
      }
    ],
    "activated": true,
    "isSubbed": false,
    "slug": "andelsboligbogen",
    "allowCatchAllSearchString": false,
    "id": 1240,
    "title": "Andelsboligbogen",
    "titleWbr": "Andels/bolig/bog/en",
    "colorHex": "5b0000",
    "emoji": "游",
    "shortDescription": "Pant og udl칝g i Andelsboligforeninger.",
    "longDescription": "I Andelsboligbogen registrerer kreditorer deres rettigheder (pant, udl칝g mv.) over andele i Andelsboligforeninger samt aktier og anparter i henholdsvis boligaktieselskaber og boliganpartsselskaber. Andelsboligbogsoverv친gningen er en overv친gning af dette. Der hentes data fra <a href=\"https://domstol.dk/tinglysningsretten/tingboegerne/andelsboligbogen/\">Andelsboligbogen</a> flere gange dagligt."
  }
}